README.rst
setup.cfg
setup.py
nyaalib/__init__.py
nyaalib/models.py
nyaalib.egg-info/PKG-INFO
nyaalib.egg-info/SOURCES.txt
nyaalib.egg-info/dependency_links.txt
nyaalib.egg-info/requires.txt
nyaalib.egg-info/top_level.txt