Metadata-Version: 1.1
Name: nyaalib
Version: 0.0.3
Summary: Python library for Nyaa
Home-page: https://github.com/kennydo/nyaalib
Author: Kenny Do
Author-email: kedo@ocf.berkeley.edu
License: MIT
Platform: UNKNOWN
Classifier: Development Status :: 3 - Alpha
Classifier: License :: OSI Approved :: MIT License
Classifier: Operating System :: OS Independent
Classifier: Programming Language :: Python
Classifier: Topic :: Communications :: File Sharing
Classifier: Topic :: Internet :: WWW/HTTP
Classifier: Topic :: Internet :: WWW/HTTP :: Indexing/Search
